DeploymentDirector/__init__.py
DeploymentDirector/cli.py
DeploymentDirector/director.py
DeploymentDirector/main.py
DeploymentDirector/rules.py
DeploymentDirector/utils.py
DeploymentDirector/actions/__init__.py
DeploymentDirector/actions/base.py
DeploymentDirector/actions/command.py
deployment_director-0.2.1.dist-info/LICENSE.txt
deployment_director-0.2.1.dist-info/METADATA
deployment_director-0.2.1.dist-info/WHEEL
deployment_director-0.2.1.dist-info/entry_points.txt
deployment_director-0.2.1.dist-info/top_level.txt
deployment_director-0.2.1.dist-info/RECORD
