Metadata-Version: 2.1
Name: deployment-director
Version: 0.2.1
Summary: UNKNOWN
Home-page: https://github.com/ushahidi/deployment-director
Author: Ushahidi Team
Author-email: team@ushahidi.com
License: MIT
Keywords: deployment,automation
Platform: UNKNOWN
Requires-Python: >=3.7
Requires-Dist: click (>6)
Requires-Dist: voluptuous (>0.10)
Requires-Dist: executor (>=18)
Requires-Dist: frozendict (>=1.2)
Requires-Dist: colorama (==0.3.9)
Requires-Dist: PyYAML (>3)
Requires-Dist: six (<2,>1)
